{
  "date": "2026-05-31",
  "requested_ids": [
    2,
    6
  ],
  "requested_articles": [
    {
      "id": 2,
      "url": "https://www.ign.com/articles/rayman-origins-remaster-leak-reveals-first-details-about-enhanced-edition-from-ubisoft",
      "en_title": "Rayman Origins Remaster Leak Reveals First Details About Enhanced Edition from Ubisoft"
    },
    {
      "id": 6,
      "url": "https://www.ign.com/articles/a-minecraft-movie-2-gets-official-title-ahead-of-july-2027-premiere",
      "en_title": "A Minecraft Movie 2 Gets Official Title Ahead of July 2027 Premiere"
    }
  ],
  "requested_at": "2026-05-31T04:26:12.766Z"
}