{
  "updated_at": "2026-06-29 01:36:57 +08:00",
  "source": "multi-source median",
  "base": "USD",
  "rates_to_cny": {
    "USD": 6.8,
    "EUR": 7.75,
    "JPY_100": 4.21,
    "GBP": 8.99,
    "KRW_100": 0.44
  },
  "validation": {
    "verified": true,
    "required_sources_min": 2,
    "source_count": 4,
    "max_cross_source_deviation_allowed": 0.02,
    "checks": {
      "USD": {
        "source_count": 4,
        "median_raw": 6.804479,
        "max_cross_source_deviation": 0.000982,
        "previous_deviation": 0.000811
      },
      "EUR": {
        "source_count": 4,
        "median_raw": 7.753429,
        "max_cross_source_deviation": 0.001299,
        "previous_deviation": 0.000442
      },
      "JPY_100": {
        "source_count": 4,
        "median_raw": 4.208374,
        "max_cross_source_deviation": 0.001194,
        "previous_deviation": 0.000386
      },
      "GBP": {
        "source_count": 4,
        "median_raw": 8.989251,
        "max_cross_source_deviation": 0.001812,
        "previous_deviation": 8.3e-05
      },
      "KRW_100": {
        "source_count": 4,
        "median_raw": 0.442973,
        "max_cross_source_deviation": 0.001168,
        "previous_deviation": 0.006757
      }
    },
    "sources": [
      {
        "name": "open-er-api",
        "url": "https://open.er-api.com/v6/latest/USD",
        "rates_to_cny": {
          "USD": 6.81116,
          "EUR": 7.757418,
          "JPY_100": 4.211998,
          "GBP": 8.992592,
          "KRW_100": 0.443296
        }
      },
      {
        "name": "exchangerate-api-v4",
        "url": "https://api.exchangerate-api.com/v4/latest/USD",
        "rates_to_cny": {
          "USD": 6.81,
          "EUR": 7.756264,
          "JPY_100": 4.211242,
          "GBP": 8.996037,
          "KRW_100": 0.443221
        }
      },
      {
        "name": "frankfurter",
        "url": "https://api.frankfurter.app/latest?from=USD&to=CNY,EUR,JPY,GBP,KRW",
        "rates_to_cny": {
          "USD": 6.7982,
          "EUR": 7.750593,
          "JPY_100": 4.205506,
          "GBP": 8.98591,
          "KRW_100": 0.442456
        }
      },
      {
        "name": "currency-api-jsdelivr",
        "url": "https://cdn.jsdelivr.net/npm/@fawazahmed0/currency-api@latest/v1/currencies/usd.json",
        "rates_to_cny": {
          "USD": 6.798959,
          "EUR": 7.743355,
          "JPY_100": 4.203349,
          "GBP": 8.972965,
          "KRW_100": 0.442725
        }
      }
    ]
  },
  "note": "CNY reference rates verified by multiple sources. Translation code must recalculate CNY amounts from this file."
}
